[
    {
        "motMetaKey": "categoryMain",
        "motMetaValues": [
            "MotorController",
            "Motor"
        ]
    },
    {
        "motMetaKey": "MotorController",
        "motMetaValues": [
            "MOTOR_CONTROLLER",
            "ANALOG_USER",
            "THERMISTOR_PCB",
            "THERMISTOR_MOSFETS_TOP",
            "THERMISTOR_MOSFETS_BOT",
            "VMONITOR_VPOS",
            "VMONITOR_VSENSE",
            "VMONITOR_VACC",
            "PROTOCOLS",
            "PROTOCOLS[1]",
            "PROTOCOLS[2]",
            "SHELL"
        ]
    },
    {
        "motMetaKey": "Motor",
        "motMetaValues": [
            "MOTORS[0]",
            "ENCODER[0]",
            "HALL[0]",
            "THERMISTOR_MOTORS[0]",
            "PID_SPEED[0]",
            "PID_FOC_IQ[0]",
            "PID_FOC_ID[0]"
        ]
    },
    {
        "motMetaKey": "unit",
        "motMetaValues": [
            "Volts",
            "Amps"
        ]
    },
    {
        "motMetaKey": "category1",
        "motMetaValues": [
            "PositionSensor",
            "PIDFeedback",
            "Temperture",
            "VoltageMonitor",
            "UserInput",
            "Protocol"
        ]
    },
    {
        "motMetaKey": "category2",
        "motMetaValues": [
            "Calibration",
            "Preferences"
        ]
    },
    {
        "motMetaKey": "category3",
        "motMetaValues": [
            "Basic",
            "Advanced",
            "Factory"
        ]
    },
    {
        "motMetaKey": "color",
        "motMetaValues": [
            "red",
            "blue",
            "black"
        ]
    }
]